MANIFEST.in
setup.py
TwinTowers/__init__.py
TwinTowers/baseline.py
TwinTowers/command.py
TwinTowers/dynamic_sampling.py
TwinTowers/evaluation.py
TwinTowers/model.py
TwinTowers/search.py
TwinTowers/train.py
TwinTowers/utils.py
TwinTowers/vector_construction.py
TwinTowers/Faiss/__init__.py
TwinTowers/Faiss/huge_db_construction.py
TwinTowers/Faiss/index_construction.py
TwinTowers/LoadingData/PkU_data.py
TwinTowers/LoadingData/__init__.py
TwinTowers/LoadingData/data_construction.py
TwinTowers/LoadingData/dataset.py
TwinTowers/LoadingData/tokenizer.py
TwinTowers/PretrainedModels/__init__.py
TwinTowers/PretrainedModels/config.py
TwinTowers/Results/__init__.py
TwinTowers/Results/format.py
TwinTowers/esm/__init__.py
TwinTowers/esm/axial_attention.py
TwinTowers/esm/constants.py
TwinTowers/esm/data.py
TwinTowers/esm/model.py
TwinTowers/esm/modules.py
TwinTowers/esm/multihead_attention.py
TwinTowers/esm/pretrained.py
TwinTowers/esm/version.py
TwinTowers/software/__init__.py
TwinTowers/software/linux_famsa
TwinTowers/software/windows_famsa.exe
twintowers.egg-info/PKG-INFO
twintowers.egg-info/SOURCES.txt
twintowers.egg-info/dependency_links.txt
twintowers.egg-info/entry_points.txt
twintowers.egg-info/requires.txt
twintowers.egg-info/top_level.txt