Metadata-Version: 2.1
Name: twintowers
Version: 0.2.2
Summary: protein homology detection using deep learning
Home-page: UNKNOWN
Author: LTEnjoy
Author-email: sujinltenjoy@gmail.com
License: UNKNOWN
Platform: UNKNOWN
